gjwt_auth/__init__.py
gjwt_auth/apps.py
gjwt_auth/models.py
gjwt_auth/mutations.py
gjwt_auth/serializers.py
gjwt_auth/utils.py
gjwt_auth/migrations/0001_initial.py
gjwt_auth/migrations/__init__.py
graphene_jwt_auth_registration-1.0.0.dist-info/DESCRIPTION.rst
graphene_jwt_auth_registration-1.0.0.dist-info/METADATA
graphene_jwt_auth_registration-1.0.0.dist-info/RECORD
graphene_jwt_auth_registration-1.0.0.dist-info/WHEEL
graphene_jwt_auth_registration-1.0.0.dist-info/metadata.json
graphene_jwt_auth_registration-1.0.0.dist-info/top_level.txt
