Metadata-Version: 2.0
Name: graphene-jwt-auth-registration
Version: 1.0.0
Summary: Authentication and registration with django graphene and JWT 
Home-page: https://github.com/fivethreeo/graphene-jwt-auth-registration
Author: Øyvind Saltvik
Author-email: oyvind.saltvik@gmail.com
License: MIT
Keywords: graphene-jwt-auth-registration
Platform: UNKNOWN
Classifier: Development Status :: 3 - Alpha
Classifier: Framework :: Django :: 2.0
Classifier: Intended Audience :: Developers
Classifier: License :: OSI Approved :: BSD License
Classifier: Natural Language :: English
Classifier: Programming Language :: Python :: 2
Classifier: Programming Language :: Python :: 2.7
Classifier: Programming Language :: Python :: 3
Classifier: Programming Language :: Python :: 3.4
Classifier: Programming Language :: Python :: 3.5
Classifier: Programming Language :: Python :: 3.6
Requires-Dist: djangorestframework-filters
Requires-Dist: djangorestframework-jwt
Requires-Dist: djoser
Requires-Dist: graphene-django
Requires-Dist: django-graphql-jwt
